{
  "enabled": true,
  "url": "https://chat.yourdomain.com",
  "token": "evGX8sBi7Z9DKXxSs44p54hM",
  "account": 1,
  "inbox": "my-session",
  "signAgent": true,
  "signSeparator": "\n",
  "autoReopen": true,
  "startPending": false,
  "mergeBrPhones": true,
  "syncContacts": false,
  "syncMessages": false,
  "syncDays": 7,
  "ignoreChats": [],
  "autoInbox": true,
  "chatwootDbHost": "localhost",
  "chatwootDbPort": 5433,
  "chatwootDbUser": "postgres",
  "chatwootDbPass": "postgres",
  "chatwootDbName": "chatwoot"
}
